npmdownloader/__init__.py
npmdownloader/__main__.py
npmdownloader/logger.py
npmdownloader/multipackagedownloader.py
npmdownloader/npmclient.py
npmdownloader/npmpackage.py
npmdownloader/packagedownloader.py
npmdownloader/utils.py
npmdownloader-1.2.1.dist-info/LICENSE.txt
npmdownloader-1.2.1.dist-info/METADATA
npmdownloader-1.2.1.dist-info/WHEEL
npmdownloader-1.2.1.dist-info/top_level.txt
npmdownloader-1.2.1.dist-info/RECORD
