Metadata-Version: 2.1
Name: npmdownloader
Version: 1.2.1
Summary: NPM Package Downloader
Home-page: https://github.com/ozelentok/npmdownloader
Author: Oz Elentok
Author-email: oz.elen@gmail.com
License: MIT
Download-URL: https://github.com/ozelentok/npmdownloader/tarball/1.2.1
Keywords: npm nodejs sinopia verdaccio offline
Platform: UNKNOWN
Classifier: Environment :: Console
Classifier: Intended Audience :: Developers
Classifier: Intended Audience :: Information Technology
Classifier: License :: OSI Approved :: MIT License
Classifier: Natural Language :: English
Classifier: Programming Language :: Python :: 3.7
Classifier: Programming Language :: Python :: 3.8
Classifier: Topic :: Software Development :: Build Tools
Classifier: Topic :: Software Development :: Version Control
Classifier: Topic :: Software Development
Classifier: Topic :: System :: Software Distribution
Requires-Python: >=3.7
Requires-Dist: node-semver
Requires-Dist: fasteners
Requires-Dist: aiohttp
Requires-Dist: aiofiles
